COPYING
MANIFEST.in
README.rst
setup.py
docs/conf.py
docs/index.rst
xbob/__init__.py
xbob.db.lfwidentification.egg-info/PKG-INFO
xbob.db.lfwidentification.egg-info/SOURCES.txt
xbob.db.lfwidentification.egg-info/dependency_links.txt
xbob.db.lfwidentification.egg-info/entry_points.txt
xbob.db.lfwidentification.egg-info/namespace_packages.txt
xbob.db.lfwidentification.egg-info/not-zip-safe
xbob.db.lfwidentification.egg-info/requires.txt
xbob.db.lfwidentification.egg-info/top_level.txt
xbob/db/__init__.py
xbob/db/lfwidentification/__init__.py
xbob/db/lfwidentification/create.py
xbob/db/lfwidentification/db.sql3
xbob/db/lfwidentification/driver.py
xbob/db/lfwidentification/models.py
xbob/db/lfwidentification/query.py
xbob/db/lfwidentification/test.py